moveread/pipelines/preprocess/__init__.py
moveread/pipelines/preprocess/__init__.pyi
moveread/pipelines/preprocess/_api.py
moveread/pipelines/preprocess/context.py
moveread/pipelines/preprocess/types.py
moveread/pipelines/preprocess/workflow.py
moveread/pipelines/preprocess/pipelines/__init__.py
moveread/pipelines/preprocess/pipelines/__init__.pyi
moveread/pipelines/preprocess/pipelines/_correct.py
moveread/pipelines/preprocess/pipelines/_descale.py
moveread/pipelines/preprocess/pipelines/_preoutput.py
moveread/pipelines/preprocess/pipelines/_select.py
moveread/pipelines/preprocess/pipelines/_validate.py
moveread/pipelines/preprocess/scripts/cli.py
moveread_pipelines_preprocess-1.0.0.dist-info/METADATA
moveread_pipelines_preprocess-1.0.0.dist-info/WHEEL
moveread_pipelines_preprocess-1.0.0.dist-info/entry_points.txt
moveread_pipelines_preprocess-1.0.0.dist-info/top_level.txt
moveread_pipelines_preprocess-1.0.0.dist-info/RECORD
